Workbook
Name Slicer_Quarter: #N/A

Sheet sales data
A1: Product | B1: Sales | C1: Expenses | D1: Profit | E1: Region | F1: Quarter
A2: Product A | B2: 100 | C2: 50 | D2: 50 | E2: Region 1 | F2: Q1
A3: Product B | B3: 200 | C3: 80 | D3: 120 | E3: Region 2 | F3: Q1
A4: Product C | B4: 150 | C4: 70 | D4: 80 | E4: Region 1 | F4: Q2
A5: Product A | B5: 250 | C5: 100 | D5: 150 | E5: Region 2 | F5: Q2
A6: Product B | B6: 180 | C6: 90 | D6: 90 | E6: Region 1 | F6: Q3
A7: Product C | B7: 120 | C7: 60 | D7: 60 | E7: Region 2 | F7: Q3
A8: Product A | B8: 300 | C8: 120 | D8: 180 | E8: Region 1 | F8: Q4
A9: Product B | B9: 220 | C9: 110 | D9: 110 | E9: Region 2 | F9: Q4
A10: Product C | B10: 280 | C10: 130 | D10: 150 | E10: Region 1 | F10: Q1
A11: Product A | B11: 320 | C11: 140 | D11: 180 | E11: Region 2 | F11: Q1
A12: Product B | B12: 190 | C12: 100 | D12: 90 | E12: Region 1 | F12: Q2
A13: Product C | B13: 210 | C13: 90 | D13: 120 | E13: Region 2 | F13: Q2
... A17: Product A | B17: 420 | C17: 200 | D17: 220 | E17: Region 2 | F17: Q4

Sheet KPI_Calculations
A1: Quarter | B1: Average sales | C1: Total expenses | D1: Maximum profit
A2: Q1 | B2: =AVERAGEIF(sales_tbl[Quarter],A2,sales_tbl[Sales]) -> 225 | C2: =SUMIF(sales_tbl[Quarter],A2,sales_tbl[Expenses]) -> 400 | D2: =_xlfn.MAXIFS(sales_tbl[Profit],sales_tbl[Quarter],A2) -> 180
A3: Q2 | B3: =AVERAGEIF(sales_tbl[Quarter],A3,sales_tbl[Sales]) -> 200 | C3: =SUMIF(sales_tbl[Quarter],A3,sales_tbl[Expenses]) -> 360 | D3: =_xlfn.MAXIFS(sales_tbl[Profit],sales_tbl[Quarter],A3) -> 150
A4: Q3 | B4: =AVERAGEIF(sales_tbl[Quarter],A4,sales_tbl[Sales]) -> 230 | C4: =SUMIF(sales_tbl[Quarter],A4,sales_tbl[Expenses]) -> 440 | D4: =_xlfn.MAXIFS(sales_tbl[Profit],sales_tbl[Quarter],A4) -> 220
A5: Q4 | B5: =AVERAGEIF(sales_tbl[Quarter],A5,sales_tbl[Sales]) -> 310 | C5: =SUMIF(sales_tbl[Quarter],A5,sales_tbl[Expenses]) -> 580 | D5: =_xlfn.MAXIFS(sales_tbl[Profit],sales_tbl[Quarter],A5) -> 220
A8: Row Labels | B8: Sum of Sales | C8: Sum of Expenses | D8: Sum of Profit
A9: Region 1
A10: Product A | B10: 780 | C10: 330 | D10: 450
A11: Product B | B11: 370 | C11: 190 | D11: 180
A12: Product C | B12: 730 | C12: 350 | D12: 380
A13: Region 1 Total | B13: 1880 | C13: 870 | D13: 1010
A14: Region 2
A15: Product A | B15: 990 | C15: 440 | D15: 550
A16: Product B | B16: 660 | C16: 320 | D16: 340
A17: Product C | B17: 330 | C17: 150 | D17: 180
A18: Region 2 Total | B18: 1980 | C18: 910 | D18: 1070
A19: Grand Total | B19: 3860 | C19: 1780 | D19: 2080

Sheet Pivot_Tables
G2: Row Labels | H2: Sum of Sales | I2: Sum of Profit | K2: Row Labels | L2: Sum of Sales | N2: Row Labels | O2: Sum of Profit
B3: Row Labels | C3: Sum of Sales | D3: Sum of Profit | G3: Q1 | H3: 900 | I3: 500 | K3: Region 2 | L3: 1980 | N3: Product A | O3: 1000
B4: Q1 | C4: 900 | D4: 500 | G4: Q2 | H4: 800 | I4: 440 | K4: Region 1 | L4: 1880 | N4: Product C | O4: 560
B5: Q2 | C5: 800 | D5: 440 | G5: Q3 | H5: 920 | I5: 480 | K5: Grand Total | L5: 3860 | N5: Product B | O5: 520
B6: Q3 | C6: 920 | D6: 480 | G6: Q4 | H6: 1240 | I6: 660 | N6: Grand Total | O6: 2080
B7: Q4 | C7: 1240 | D7: 660 | G7: Grand Total | H7: 3860 | I7: 2080 | K7: Quarter | L7: (All)
B8: Grand Total | C8: 3860 | D8: 2080 | K8: Region | L8: (All)
G9: Row Labels | H9: Sum of Expenses
G10: Q1 | H10: 400 | K10: Sum of Sales | L10: Sum of Expenses | M10: Sum of Profit | N10: Average of Sales
G11: Q2 | H11: 360 | K11: 3860 | L11: 1780 | M11: 2080 | N11: 241.25
G12: Q3 | H12: 440
B13: Row Labels | C13: Sum of Sales | G13: Q4 | H13: 580
B14: Region 1 | C14: 1880 | G14: Grand Total | H14: 1780
B15: Region 2 | C15: 1980
B16: Grand Total | C16: 3860
C20: Row Labels | D20: Sum of Profit
C21: Product A | D21: 1000
C22: Product B | D22: 520
C23: Product C | D23: 560
C24: Grand Total | D24: 2080

Sheet Pivot_Charts

Sheet Dashboard
A1: Sales Analysis Dashboard
B4: Total Sales | F4: Profit Margin % | J4: Total Profit | N4: Business Recommendation Panel
B6: =GETPIVOTDATA("Sum of Sales",Pivot_Tables!$K$10) -> 3860 | F6: =GETPIVOTDATA("Profit",Pivot_Tables!$N$2)/GETPIVOTDATA("Sales",Pivot_Tables!$K$2) -> 0.5388601 | J6: =GETPIVOTDATA("Sum of Profit",Pivot_Tables!$K$10) -> 2080 | N6: ="Focus on "&F18&" in "&F12&", as it currently delivers highest overall performance." -> Focus on Product A in Region 2, as it currently delivers highest overall performance.
B10: Total records | F10: Best Region | J10: Total Expenses
B12: =COUNTA(sales_tbl[Product]) -> 16 | F12: =Pivot_Tables!K3 -> Region 2 | J12: =GETPIVOTDATA("Sum of Expenses",Pivot_Tables!$K$10) -> 1780
B16: Average sales | F16: Best Product | O16: Quarter | P16: (All)
O17: Region | P17: (All)
B18: =GETPIVOTDATA("Average of Sales",Pivot_Tables!$K$10) -> 241.25 | F18: =Pivot_Tables!N3 -> Product A
O19: Sum of Sales | P19: Sum of Expenses | Q19: Sum of Profit | R19: Average of Sales
O20: 3860 | P20: 1780 | Q20: 2080 | R20: 241.25
